smallCompanyType/__init__.py
smallCompanyType/smallCompanyType.py
smallCompanyType/models/company_classifier.h5
smallCompanyType/models/encode.pkl
smallCompanyType-2.2.dist-info/METADATA
smallCompanyType-2.2.dist-info/WHEEL
smallCompanyType-2.2.dist-info/top_level.txt
smallCompanyType-2.2.dist-info/RECORD
